domain_collector/__init__.py
domain_collector/main.py
domain_collector/utils/__init__.py
domain_collector/utils/browser.py
domain_collector/utils/file_operations.py
domain_collector-0.1.4.dist-info/METADATA
domain_collector-0.1.4.dist-info/WHEEL
domain_collector-0.1.4.dist-info/entry_points.txt
domain_collector-0.1.4.dist-info/licenses/LICENSE
domain_collector-0.1.4.dist-info/RECORD
