Metadata-Version: 2.4
Name: domain-collector
Version: 0.1.4
Summary: Collect domains with ease
Author-email: "Maxim (neiromaster) Gavrilenko" <parrysh@mail.ru>
License-File: LICENSE
Requires-Python: >=3.9
Requires-Dist: playwright>=1.49.1
